ufile/__init__.py
ufile/auth.py
ufile/baseufile.py
ufile/bucketmanager.py
ufile/compact.py
ufile/config.py
ufile/filemanager.py
ufile/httprequest.py
ufile/logger.py
ufile/multipartuploadufile.py
ufile/util.py
ufile-3.2.11.dist-info/LICENSE
ufile-3.2.11.dist-info/METADATA
ufile-3.2.11.dist-info/WHEEL
ufile-3.2.11.dist-info/top_level.txt
ufile-3.2.11.dist-info/RECORD
